xyolo/__init__.py
xyolo/config.py
xyolo/convert.py
xyolo/init_yolo.py
xyolo/preprocessing.py
xyolo/xyolo_data/FiraMono-Medium.otf
xyolo/xyolo_data/SIL Open Font License.txt
xyolo/xyolo_data/coco_classes.txt
xyolo/xyolo_data/yolo_anchors.txt
xyolo/xyolo_data/yolov3.cfg
xyolo/yolo3/__init__.py
xyolo/yolo3/model.py
xyolo/yolo3/utils.py
xyolo/yolo3/yolo.py
xyolo-0.1.6.dist-info/LICENSE
xyolo-0.1.6.dist-info/METADATA
xyolo-0.1.6.dist-info/WHEEL
xyolo-0.1.6.dist-info/top_level.txt
xyolo-0.1.6.dist-info/RECORD
