Metadata-Version: 2.1
Name: xyolo
Version: 0.1.6
Summary: xyolo is a highly encapsulated YOLO v3 library implemented in Python.With xyolo, you can easily complete the training and calling of the yolo3 target detection task with just a few lines of Python code.
Home-page: https://github.com/AaronJny/xyolo
Author: AaronJny
Author-email: aaronjny7@gmail.com
License: UNKNOWN
Platform: UNKNOWN
Classifier: Programming Language :: Python :: 3
Classifier: License :: OSI Approved :: MIT License
Classifier: Operating System :: OS Independent
Requires-Python: >=3.6
Requires-Dist: tensorflow (>=2.2)
Requires-Dist: numpy (<1.19.0,>=1.18.1)
Requires-Dist: pillow (>=7.0.0)
Requires-Dist: matplotlib (>=3.1.3)
Requires-Dist: loguru (>=0.5.1)
Requires-Dist: requests (>=2.22.0)
Requires-Dist: tqdm (>=4.42.1)
Requires-Dist: lxml (>=4.5.0)
Requires-Dist: opencv-python (>=4.2.0)
